dynamicsizerecarray/__init__.py
dynamicsizerecarray/version.py
dynamicsizerecarray-0.1.0.dist-info/licenses/LICENSE
dynamicsizerecarray-0.1.0.dist-info/METADATA
dynamicsizerecarray-0.1.0.dist-info/WHEEL
dynamicsizerecarray-0.1.0.dist-info/top_level.txt
dynamicsizerecarray-0.1.0.dist-info/RECORD
