Metadata-Version: 2.4
Name: dynamicsizerecarray
Version: 0.1.0
Summary: Like a numpy-recarray but dynamically appendable.
Home-page: https://github.com/cherenkov-plenoscope/dynamicsizerecarray
Author: Sebastian Achim Mueller
Author-email: sebastian-achim.mueller@mpi-hd.mpg.de
Classifier: Programming Language :: Python :: 3
Classifier: License :: OSI Approved :: MIT License
Classifier: Operating System :: OS Independent
Classifier: Natural Language :: English
License-File: LICENSE
Dynamic: author
Dynamic: author-email
Dynamic: classifier
Dynamic: description
Dynamic: description-content-type
Dynamic: home-page
Dynamic: license-file
Dynamic: summary
